MAYA/__init__.py
MAYA/date.py
MAYA/filerepos.py
MAYA/repos.py
MAYA/uform.py
MAYA/uuid.py
MAYA/vsmf.py
MAYA/VIA/__init__.py
MAYA/VIA/caching_repos/__init__.py
MAYA/VIA/repos/__init__.py
MAYA/VIA/repos/tests/test_partial_set.py
MAYA/VIA/roles/__init__.py
MAYA/VIA/roles/address.py
MAYA/VIA/roles/address_coll.py
MAYA/VIA/roles/bibliographic_entry.py
MAYA/VIA/roles/collection.py
MAYA/VIA/roles/entity.py
MAYA/VIA/roles/person.py
MAYA/VIA/roles/phone_num_coll.py
MAYA/VIA/roles/role.py
MAYA/VIA/roles/sar.py
MAYA/VIA/roles/telephone_number.py
MAYA/VIA/roles/ter.py
MAYA/VIA/roles/user.py
MAYA/VIA/roles/tests/unittests/test_roles.py
MAYA/VIA/threadsafe_repos/__init__.py
MAYA/VIA/threadsafe_repos/tests/test_partial_set.py
MAYA/VIA/uform/__init__.py
MAYA/VIA/uuid/__init__.py
MAYA/VIA/vsmf/__init__.py
MAYA/VIA/vsmf/_build_ext.py
MAYA/VIA/vsmf/_tests/test_vsmf.py
MAYA/VIA/webapps/__init__.py
MAYA/VIA/webapps/editattr.py
MAYA/VIA/webapps/rolelib.py
MAYA/VIA/webapps/roleviewer.py
MAYA/VIA/webapps/uf.py
MAYA/VIA/webapps/val.py
MAYA/datatypes/__init__.py
MAYA/role/DN_client.py
MAYA/role/LP_base_project.py
MAYA/role/LP_company.py
MAYA/role/LP_employee.py
MAYA/role/LP_project.py
MAYA/role/LP_subproject.py
MAYA/role/__init__.py
MAYA/role/address.py
MAYA/role/addresses_collection.py
MAYA/role/bibliographic_entry.py
MAYA/role/collection.py
MAYA/role/country.py
MAYA/role/doc_num.py
MAYA/role/doc_num_revision.py
MAYA/role/entity.py
MAYA/role/person.py
MAYA/role/phone_numbers_collection.py
MAYA/role/role.py
MAYA/role/sar.py
MAYA/role/telephone_number.py
MAYA/role/ter.py
MAYA/role/user.py
MAYA/unittest/__init__.py
MAYA/unittest/example.py
MAYA/unittest/reposunittest.py
MAYA/utils/CachingRepository.py
MAYA/utils/__init__.py
MAYA/utils/adhash.py
MAYA/utils/authclient.py
MAYA/utils/btdbrepos.py
MAYA/utils/buckets.py
MAYA/utils/cache.py
MAYA/utils/conflicts.py
MAYA/utils/crypto.py
MAYA/utils/date.py
MAYA/utils/filerepos.py
vialib-1.0.0.dist-info/METADATA
vialib-1.0.0.dist-info/RECORD
vialib-1.0.0.dist-info/WHEEL
vialib-1.0.0.dist-info/top_level.txt
