Metadata-Version: 2.1
Name: vialib
Version: 1.0.0
Summary: MAYA VIA Python Libraries
Home-page: UNKNOWN
Author: MAYA Design
Author-email: jeffsenn@gmail.com
License: UNKNOWN
Platform: UNKNOWN
